stardist/__init__.py
stardist/big.py
stardist/bioimageio_utils.py
stardist/matching.py
stardist/nms.py
stardist/rays3d.py
stardist/sample_patches.py
stardist/utils.py
stardist/version.py
stardist/data/__init__.py
stardist/data/images/histo.jpg
stardist/data/images/img2d.tif
stardist/data/images/img3d.tif
stardist/data/images/mask2d.tif
stardist/data/images/mask3d.tif
stardist/geometry/__init__.py
stardist/geometry/geom2d.py
stardist/geometry/geom3d.py
stardist/kernels/stardist2d.cl
stardist/kernels/stardist3d.cl
stardist/lib/stardist2d.cpython-312-x86_64-linux-gnu.so
stardist/lib/stardist3d.cpython-312-x86_64-linux-gnu.so
stardist/models/__init__.py
stardist/models/base.py
stardist/models/model2d.py
stardist/models/model3d.py
stardist/plot/__init__.py
stardist/plot/plot.py
stardist/plot/render.py
stardist/scripts/__init__.py
stardist/scripts/predict2d.py
stardist/scripts/predict3d.py
stardist.libs/libgomp-e985bcbb.so.1.0.0
stardist-0.9.2.dist-info/METADATA
stardist-0.9.2.dist-info/WHEEL
stardist-0.9.2.dist-info/entry_points.txt
stardist-0.9.2.dist-info/top_level.txt
stardist-0.9.2.dist-info/RECORD
stardist-0.9.2.dist-info/licenses/LICENSE.txt
stardist-0.9.2.dist-info/sboms/auditwheel.cdx.json
