Metadata-Version: 2.1
Name: stardist
Version: 0.9.2
Summary: StarDist - Object Detection with Star-convex Shapes
Home-page: https://github.com/stardist/stardist
Author: Uwe Schmidt, Martin Weigert
Author-email: research@uweschmidt.org, martin.weigert@epfl.ch
License: BSD-3-Clause
Classifier: Development Status :: 4 - Beta
Classifier: Intended Audience :: Science/Research
Classifier: Topic :: Scientific/Engineering
Classifier: License :: OSI Approved :: BSD License
Classifier: Operating System :: OS Independent
Classifier: Programming Language :: Python :: 3.6
Classifier: Programming Language :: Python :: 3.7
Classifier: Programming Language :: Python :: 3.8
Classifier: Programming Language :: Python :: 3.9
Classifier: Programming Language :: Python :: 3.10
Classifier: Programming Language :: Python :: 3.11
Classifier: Programming Language :: Python :: 3.12
Classifier: Programming Language :: Python :: 3.13
Requires-Python: >=3.6
License-File: LICENSE.txt
Requires-Dist: csbdeep>=0.8.2
Requires-Dist: scikit-image
Requires-Dist: imageio
Requires-Dist: numba; platform_system != "Darwin" or platform_machine == "arm64"
Requires-Dist: numba<=0.62.1; platform_system == "Darwin" and platform_machine != "arm64"
Requires-Dist: llvmlite<=0.45.1; platform_system == "Darwin" and platform_machine != "arm64"
Requires-Dist: numpy<3; python_version >= "3.9"
Provides-Extra: bioimageio
Requires-Dist: bioimageio.core>=0.5.0; extra == "bioimageio"
Requires-Dist: importlib-metadata; extra == "bioimageio"
Provides-Extra: test
Requires-Dist: pytest; python_version < "3.7" and extra == "test"
Requires-Dist: pytest>=7.2.0; python_version >= "3.7" and extra == "test"
Provides-Extra: tf1
Requires-Dist: csbdeep[tf1]>=0.8.2; extra == "tf1"
